bluebird/__init__.py
bluebird/data.py
bluebird/exceptions.py
bluebird/metrics.py
bluebird/nn.py
bluebird/progress_tracker.py
bluebird/regularizators.py
bluebird/tensor.py
bluebird/utils.py
bluebird/weight_initializers.py
bluebird/activations/__init__.py
bluebird/activations/activation.py
bluebird/activations/relu.py
bluebird/activations/sigmoid.py
bluebird/activations/softmax.py
bluebird/activations/tanh.py
bluebird/datasets/__init__.py
bluebird/datasets/mnist.py
bluebird/layers/__init__.py
bluebird/layers/dense.py
bluebird/layers/dropout.py
bluebird/layers/flatten.py
bluebird/layers/input.py
bluebird/layers/layer.py
bluebird/layers/linear.py
bluebird/loss/CategoricalCrossEntropy.py
bluebird/loss/MSE.py
bluebird/loss/__init__.py
bluebird/loss/loss.py
bluebird/optimizers/__init__.py
bluebird/optimizers/adagrad.py
bluebird/optimizers/adam.py
bluebird/optimizers/nestov_momentum.py
bluebird/optimizers/optimizer.py
bluebird/optimizers/sgd.py
examples/__init__.py
examples/mnist.py
bluebird_stoick01-0.0.2.dist-info/LICENSE
bluebird_stoick01-0.0.2.dist-info/METADATA
bluebird_stoick01-0.0.2.dist-info/WHEEL
bluebird_stoick01-0.0.2.dist-info/top_level.txt
bluebird_stoick01-0.0.2.dist-info/RECORD
