Metadata-Version: 2.1
Name: bluebird-stoick01
Version: 0.0.2
Summary: Deep learning library
Home-page: https://github.com/Stoick01/bluebird
Author: Gordan Prastalo
Author-email: gordan.prastalo.gp@gmail.com
License: MIT
Platform: UNKNOWN
Classifier: Programming Language :: Python :: 3
Classifier: License :: OSI Approved :: MIT License
Classifier: Operating System :: OS Independent
Requires-Python: >=3.6
Requires-Dist: numpy (==1.19.2)
